ewstools/__init__.py
ewstools/core.py
ewstools/helpers.py
ewstools/models.py
ewstools-2.1.2.dist-info/LICENSE
ewstools-2.1.2.dist-info/METADATA
ewstools-2.1.2.dist-info/WHEEL
ewstools-2.1.2.dist-info/top_level.txt
ewstools-2.1.2.dist-info/RECORD
