Metadata-Version: 2.1
Name: ewstools
Version: 2.1.2
Summary: Python package to compute early warning signals (EWS) 
Home-page: https://github.com/ThomasMBury/ewstools
Author: Thomas M Bury
Author-email: tombury182@gmail.com
Classifier: Programming Language :: Python :: 3
Classifier: License :: OSI Approved :: MIT License
Classifier: Operating System :: OS Independent
License-File: LICENSE
Requires-Dist: pandas (>=0.23.0)
Requires-Dist: numpy (>=1.14.0)
Requires-Dist: plotly (>=2.3.0)
Requires-Dist: lmfit (>=0.9.0)
Requires-Dist: arch (>=4.4)
Requires-Dist: statsmodels (>=0.9.0)
Requires-Dist: scipy (>=1.0.1)
Requires-Dist: deprecation (>=2.0)
Requires-Dist: entropyhub (>=2.0)
